{"@context":"http://iiif.io/api/presentation/2/context.json","@id":"https://fuldig.hs-fulda.de/viewer/rest/iiif/manifests/PPN439972744/manifest","@type":"sc:Manifest","label":"Pfaltzgraff Churfürst spricht zu dem Duca de Alba: ...","metadata":[{"label":[{"@value":"Titel","@language":"de"},{"@value":"Title","@language":"en"},{"@value":"Título","@language":"es"}],"value":"Pfaltzgraff Churfürst spricht zu dem Duca de Alba: ..."}],"thumbnail":{"@id":"https://fuldig.hs-fulda.de/viewer/rest/image/PPN439972744/00000001.tif/full/!200,220/0/default.jpg","@type":"dcTypes:Image","service":{"@context":"http://iiif.io/api/image/2/context.json","@id":"https://fuldig.hs-fulda.de/viewer/rest/image/PPN439972744/00000001.tif","profile":"http://iiif.io/api/image/2/level2.json"}},"attribution":[{"@value":"Hochschul- und Landesbibliothek Fulda","@language":"de"},{"@value":"Goobi viewer","@language":"en"},{"@value":"Goobi viewer","@language":"es"}],"logo":{"@id":"https://fuldig.hs-fulda.de/viewer/resources/themes/hlbf/images/dfgviewer_intranda.jpg","@type":"dcTypes:Image"},"rendering":[{"@id":"https://fuldig.hs-fulda.de/viewer/image/PPN439972744/1/LOG_0000/","label":"goobi viewer","format":"text/html"},{"@id":"https://fuldig.hs-fulda.de/viewer/rest/pdf/mets/PPN439972744.xml/Pfaltzgraff_Churfrst_spricht_zu_dem_Duca_de_Alba_.pdf?watermarkText=https%3A%2F%2Ffuldig.hs-fulda.de%2Fviewer%2Fimage%2FPPN439972744%2F1%2F","label":"PDF","format":"applocation/pdf"}],"seeAlso":{"@id":"https://fuldig.hs-fulda.de/viewer/metsresolver?id=PPN439972744","label":"METS/MODS","format":"text/xml"},"sequences":[{"@id":"https://fuldig.hs-fulda.de/viewer/rest/iiif/manifests/PPN439972744/sequence/basic","@type":"sc:Sequence","viewingHint":"paged","within":"https://fuldig.hs-fulda.de/viewer/rest/iiif/manifests/PPN439972744/manifest","canvases":[{"@id":"https://fuldig.hs-fulda.de/viewer/rest/iiif/manifests/PPN439972744/canvas/1","@type":"sc:Canvas","label":" - ","thumbnail":{"@id":"https://fuldig.hs-fulda.de/viewer/rest/image/PPN439972744/00000001.tif/full/!200,220/0/default.jpg","@type":"dcTypes:Image"},"rendering":{"@id":"https://fuldig.hs-fulda.de/viewer/image/PPN439972744/1/","label":"goobi viewer","format":"text/html"},"within":"https://fuldig.hs-fulda.de/viewer/rest/iiif/manifests/PPN439972744/sequence/basic","width":4185,"height":5907,"images":[{"@id":"https://fuldig.hs-fulda.de/viewer/rest/iiif/manifests/PPN439972744/canvas/1/image/1","@type":"oa:Annotation","motivation":"sc:painting","on":"https://fuldig.hs-fulda.de/viewer/rest/iiif/manifests/PPN439972744/canvas/1","resource":{"@id":"https://fuldig.hs-fulda.de/viewer/rest/image/PPN439972744/00000001.tif/full/!200,220/0/default.jpg","@type":"dcTypes:Image","width":4185,"height":5907,"format":"image/jpeg","service":{"@context":"http://iiif.io/api/image/2/context.json","@id":"https://fuldig.hs-fulda.de/viewer/rest/image/PPN439972744/00000001.tif","profile":"http://iiif.io/api/image/2/level2.json"}}}],"otherContent":[{"@id":"https://fuldig.hs-fulda.de/viewer/rest/iiif/manifests/PPN439972744/list/1/PDF","@type":"sc:AnnotationList","label":"PDF"}]},{"@id":"https://fuldig.hs-fulda.de/viewer/rest/iiif/manifests/PPN439972744/canvas/2","@type":"sc:Canvas","label":" - ","thumbnail":{"@id":"https://fuldig.hs-fulda.de/viewer/rest/image/PPN439972744/00000002.tif/full/!200,220/0/default.jpg","@type":"dcTypes:Image"},"rendering":{"@id":"https://fuldig.hs-fulda.de/viewer/image/PPN439972744/2/","label":"goobi viewer","format":"text/html"},"within":"https://fuldig.hs-fulda.de/viewer/rest/iiif/manifests/PPN439972744/sequence/basic","width":4210,"height":5932,"images":[{"@id":"https://fuldig.hs-fulda.de/viewer/rest/iiif/manifests/PPN439972744/canvas/2/image/1","@type":"oa:Annotation","motivation":"sc:painting","on":"https://fuldig.hs-fulda.de/viewer/rest/iiif/manifests/PPN439972744/canvas/2","resource":{"@id":"https://fuldig.hs-fulda.de/viewer/rest/image/PPN439972744/00000002.tif/full/!200,220/0/default.jpg","@type":"dcTypes:Image","width":4210,"height":5932,"format":"image/jpeg","service":{"@context":"http://iiif.io/api/image/2/context.json","@id":"https://fuldig.hs-fulda.de/viewer/rest/image/PPN439972744/00000002.tif","profile":"http://iiif.io/api/image/2/level2.json"}}}],"otherContent":[{"@id":"https://fuldig.hs-fulda.de/viewer/rest/iiif/manifests/PPN439972744/list/2/PDF","@type":"sc:AnnotationList","label":"PDF"}]},{"@id":"https://fuldig.hs-fulda.de/viewer/rest/iiif/manifests/PPN439972744/canvas/3","@type":"sc:Canvas","label":" - ","thumbnail":{"@id":"https://fuldig.hs-fulda.de/viewer/rest/image/PPN439972744/00000003.tif/full/!200,220/0/default.jpg","@type":"dcTypes:Image"},"rendering":{"@id":"https://fuldig.hs-fulda.de/viewer/image/PPN439972744/3/","label":"goobi viewer","format":"text/html"},"within":"https://fuldig.hs-fulda.de/viewer/rest/iiif/manifests/PPN439972744/sequence/basic","width":4080,"height":5818,"images":[{"@id":"https://fuldig.hs-fulda.de/viewer/rest/iiif/manifests/PPN439972744/canvas/3/image/1","@type":"oa:Annotation","motivation":"sc:painting","on":"https://fuldig.hs-fulda.de/viewer/rest/iiif/manifests/PPN439972744/canvas/3","resource":{"@id":"https://fuldig.hs-fulda.de/viewer/rest/image/PPN439972744/00000003.tif/full/!200,220/0/default.jpg","@type":"dcTypes:Image","width":4080,"height":5818,"format":"image/jpeg","service":{"@context":"http://iiif.io/api/image/2/context.json","@id":"https://fuldig.hs-fulda.de/viewer/rest/image/PPN439972744/00000003.tif","profile":"http://iiif.io/api/image/2/level2.json"}}}],"otherContent":[{"@id":"https://fuldig.hs-fulda.de/viewer/rest/iiif/manifests/PPN439972744/list/3/PDF","@type":"sc:AnnotationList","label":"PDF"}]},{"@id":"https://fuldig.hs-fulda.de/viewer/rest/iiif/manifests/PPN439972744/canvas/4","@type":"sc:Canvas","label":" - ","thumbnail":{"@id":"https://fuldig.hs-fulda.de/viewer/rest/image/PPN439972744/00000004.tif/full/!200,220/0/default.jpg","@type":"dcTypes:Image"},"rendering":{"@id":"https://fuldig.hs-fulda.de/viewer/image/PPN439972744/4/","label":"goobi viewer","format":"text/html"},"within":"https://fuldig.hs-fulda.de/viewer/rest/iiif/manifests/PPN439972744/sequence/basic","width":3878,"height":5875,"images":[{"@id":"https://fuldig.hs-fulda.de/viewer/rest/iiif/manifests/PPN439972744/canvas/4/image/1","@type":"oa:Annotation","motivation":"sc:painting","on":"https://fuldig.hs-fulda.de/viewer/rest/iiif/manifests/PPN439972744/canvas/4","resource":{"@id":"https://fuldig.hs-fulda.de/viewer/rest/image/PPN439972744/00000004.tif/full/!200,220/0/default.jpg","@type":"dcTypes:Image","width":3878,"height":5875,"format":"image/jpeg","service":{"@context":"http://iiif.io/api/image/2/context.json","@id":"https://fuldig.hs-fulda.de/viewer/rest/image/PPN439972744/00000004.tif","profile":"http://iiif.io/api/image/2/level2.json"}}}],"otherContent":[{"@id":"https://fuldig.hs-fulda.de/viewer/rest/iiif/manifests/PPN439972744/list/4/PDF","@type":"sc:AnnotationList","label":"PDF"}]},{"@id":"https://fuldig.hs-fulda.de/viewer/rest/iiif/manifests/PPN439972744/canvas/5","@type":"sc:Canvas","label":" - ","thumbnail":{"@id":"https://fuldig.hs-fulda.de/viewer/rest/image/PPN439972744/00000005.tif/full/!200,220/0/default.jpg","@type":"dcTypes:Image"},"rendering":{"@id":"https://fuldig.hs-fulda.de/viewer/image/PPN439972744/5/","label":"goobi viewer","format":"text/html"},"within":"https://fuldig.hs-fulda.de/viewer/rest/iiif/manifests/PPN439972744/sequence/basic","width":1896,"height":1637,"images":[{"@id":"https://fuldig.hs-fulda.de/viewer/rest/iiif/manifests/PPN439972744/canvas/5/image/1","@type":"oa:Annotation","motivation":"sc:painting","on":"https://fuldig.hs-fulda.de/viewer/rest/iiif/manifests/PPN439972744/canvas/5","resource":{"@id":"https://fuldig.hs-fulda.de/viewer/rest/image/PPN439972744/00000005.tif/full/!200,220/0/default.jpg","@type":"dcTypes:Image","width":1896,"height":1637,"format":"image/jpeg","service":{"@context":"http://iiif.io/api/image/2/context.json","@id":"https://fuldig.hs-fulda.de/viewer/rest/image/PPN439972744/00000005.tif","profile":"http://iiif.io/api/image/2/level2.json"}}}],"otherContent":[{"@id":"https://fuldig.hs-fulda.de/viewer/rest/iiif/manifests/PPN439972744/list/5/PDF","@type":"sc:AnnotationList","label":"PDF"}]},{"@id":"https://fuldig.hs-fulda.de/viewer/rest/iiif/manifests/PPN439972744/canvas/6","@type":"sc:Canvas","label":" - ","thumbnail":{"@id":"https://fuldig.hs-fulda.de/viewer/rest/image/PPN439972744/00000006.tif/full/!200,220/0/default.jpg","@type":"dcTypes:Image"},"rendering":{"@id":"https://fuldig.hs-fulda.de/viewer/image/PPN439972744/6/","label":"goobi viewer","format":"text/html"},"within":"https://fuldig.hs-fulda.de/viewer/rest/iiif/manifests/PPN439972744/sequence/basic","width":1961,"height":1621,"images":[{"@id":"https://fuldig.hs-fulda.de/viewer/rest/iiif/manifests/PPN439972744/canvas/6/image/1","@type":"oa:Annotation","motivation":"sc:painting","on":"https://fuldig.hs-fulda.de/viewer/rest/iiif/manifests/PPN439972744/canvas/6","resource":{"@id":"https://fuldig.hs-fulda.de/viewer/rest/image/PPN439972744/00000006.tif/full/!200,220/0/default.jpg","@type":"dcTypes:Image","width":1961,"height":1621,"format":"image/jpeg","service":{"@context":"http://iiif.io/api/image/2/context.json","@id":"https://fuldig.hs-fulda.de/viewer/rest/image/PPN439972744/00000006.tif","profile":"http://iiif.io/api/image/2/level2.json"}}}],"otherContent":[{"@id":"https://fuldig.hs-fulda.de/viewer/rest/iiif/manifests/PPN439972744/list/6/PDF","@type":"sc:AnnotationList","label":"PDF"}]},{"@id":"https://fuldig.hs-fulda.de/viewer/rest/iiif/manifests/PPN439972744/canvas/7","@type":"sc:Canvas","label":"1r","thumbnail":{"@id":"https://fuldig.hs-fulda.de/viewer/rest/image/PPN439972744/00000007.tif/full/!200,220/0/default.jpg","@type":"dcTypes:Image"},"rendering":{"@id":"https://fuldig.hs-fulda.de/viewer/image/PPN439972744/7/","label":"goobi viewer","format":"text/html"},"within":"https://fuldig.hs-fulda.de/viewer/rest/iiif/manifests/PPN439972744/sequence/basic","width":3660,"height":5543,"images":[{"@id":"https://fuldig.hs-fulda.de/viewer/rest/iiif/manifests/PPN439972744/canvas/7/image/1","@type":"oa:Annotation","motivation":"sc:painting","on":"https://fuldig.hs-fulda.de/viewer/rest/iiif/manifests/PPN439972744/canvas/7","resource":{"@id":"https://fuldig.hs-fulda.de/viewer/rest/image/PPN439972744/00000007.tif/full/!200,220/0/default.jpg","@type":"dcTypes:Image","width":3660,"height":5543,"format":"image/jpeg","service":{"@context":"http://iiif.io/api/image/2/context.json","@id":"https://fuldig.hs-fulda.de/viewer/rest/image/PPN439972744/00000007.tif","profile":"http://iiif.io/api/image/2/level2.json"}}}],"otherContent":[{"@id":"https://fuldig.hs-fulda.de/viewer/rest/iiif/manifests/PPN439972744/list/7/PDF","@type":"sc:AnnotationList","label":"PDF"}]},{"@id":"https://fuldig.hs-fulda.de/viewer/rest/iiif/manifests/PPN439972744/canvas/8","@type":"sc:Canvas","label":"1v","thumbnail":{"@id":"https://fuldig.hs-fulda.de/viewer/rest/image/PPN439972744/00000008.tif/full/!200,220/0/default.jpg","@type":"dcTypes:Image"},"rendering":{"@id":"https://fuldig.hs-fulda.de/viewer/image/PPN439972744/8/","label":"goobi viewer","format":"text/html"},"within":"https://fuldig.hs-fulda.de/viewer/rest/iiif/manifests/PPN439972744/sequence/basic","width":3619,"height":5478,"images":[{"@id":"https://fuldig.hs-fulda.de/viewer/rest/iiif/manifests/PPN439972744/canvas/8/image/1","@type":"oa:Annotation","motivation":"sc:painting","on":"https://fuldig.hs-fulda.de/viewer/rest/iiif/manifests/PPN439972744/canvas/8","resource":{"@id":"https://fuldig.hs-fulda.de/viewer/rest/image/PPN439972744/00000008.tif/full/!200,220/0/default.jpg","@type":"dcTypes:Image","width":3619,"height":5478,"format":"image/jpeg","service":{"@context":"http://iiif.io/api/image/2/context.json","@id":"https://fuldig.hs-fulda.de/viewer/rest/image/PPN439972744/00000008.tif","profile":"http://iiif.io/api/image/2/level2.json"}}}],"otherContent":[{"@id":"https://fuldig.hs-fulda.de/viewer/rest/iiif/manifests/PPN439972744/list/8/PDF","@type":"sc:AnnotationList","label":"PDF"}]},{"@id":"https://fuldig.hs-fulda.de/viewer/rest/iiif/manifests/PPN439972744/canvas/9","@type":"sc:Canvas","label":"2r","thumbnail":{"@id":"https://fuldig.hs-fulda.de/viewer/rest/image/PPN439972744/00000009.tif/full/!200,220/0/default.jpg","@type":"dcTypes:Image"},"rendering":{"@id":"https://fuldig.hs-fulda.de/viewer/image/PPN439972744/9/","label":"goobi viewer","format":"text/html"},"within":"https://fuldig.hs-fulda.de/viewer/rest/iiif/manifests/PPN439972744/sequence/basic","width":3668,"height":5543,"images":[{"@id":"https://fuldig.hs-fulda.de/viewer/rest/iiif/manifests/PPN439972744/canvas/9/image/1","@type":"oa:Annotation","motivation":"sc:painting","on":"https://fuldig.hs-fulda.de/viewer/rest/iiif/manifests/PPN439972744/canvas/9","resource":{"@id":"https://fuldig.hs-fulda.de/viewer/rest/image/PPN439972744/00000009.tif/full/!200,220/0/default.jpg","@type":"dcTypes:Image","width":3668,"height":5543,"format":"image/jpeg","service":{"@context":"http://iiif.io/api/image/2/context.json","@id":"https://fuldig.hs-fulda.de/viewer/rest/image/PPN439972744/00000009.tif","profile":"http://iiif.io/api/image/2/level2.json"}}}],"otherContent":[{"@id":"https://fuldig.hs-fulda.de/viewer/rest/iiif/manifests/PPN439972744/list/9/PDF","@type":"sc:AnnotationList","label":"PDF"}]},{"@id":"https://fuldig.hs-fulda.de/viewer/rest/iiif/manifests/PPN439972744/canvas/10","@type":"sc:Canvas","label":"2v","thumbnail":{"@id":"https://fuldig.hs-fulda.de/viewer/rest/image/PPN439972744/00000010.tif/full/!200,220/0/default.jpg","@type":"dcTypes:Image"},"rendering":{"@id":"https://fuldig.hs-fulda.de/viewer/image/PPN439972744/10/","label":"goobi viewer","format":"text/html"},"within":"https://fuldig.hs-fulda.de/viewer/rest/iiif/manifests/PPN439972744/sequence/basic","width":3619,"height":5478,"images":[{"@id":"https://fuldig.hs-fulda.de/viewer/rest/iiif/manifests/PPN439972744/canvas/10/image/1","@type":"oa:Annotation","motivation":"sc:painting","on":"https://fuldig.hs-fulda.de/viewer/rest/iiif/manifests/PPN439972744/canvas/10","resource":{"@id":"https://fuldig.hs-fulda.de/viewer/rest/image/PPN439972744/00000010.tif/full/!200,220/0/default.jpg","@type":"dcTypes:Image","width":3619,"height":5478,"format":"image/jpeg","service":{"@context":"http://iiif.io/api/image/2/context.json","@id":"https://fuldig.hs-fulda.de/viewer/rest/image/PPN439972744/00000010.tif","profile":"http://iiif.io/api/image/2/level2.json"}}}],"otherContent":[{"@id":"https://fuldig.hs-fulda.de/viewer/rest/iiif/manifests/PPN439972744/list/10/PDF","@type":"sc:AnnotationList","label":"PDF"}]},{"@id":"https://fuldig.hs-fulda.de/viewer/rest/iiif/manifests/PPN439972744/canvas/11","@type":"sc:Canvas","label":" - ","thumbnail":{"@id":"https://fuldig.hs-fulda.de/viewer/rest/image/PPN439972744/00000011.tif/full/!200,220/0/default.jpg","@type":"dcTypes:Image"},"rendering":{"@id":"https://fuldig.hs-fulda.de/viewer/image/PPN439972744/11/","label":"goobi viewer","format":"text/html"},"within":"https://fuldig.hs-fulda.de/viewer/rest/iiif/manifests/PPN439972744/sequence/basic","width":3991,"height":5899,"images":[{"@id":"https://fuldig.hs-fulda.de/viewer/rest/iiif/manifests/PPN439972744/canvas/11/image/1","@type":"oa:Annotation","motivation":"sc:painting","on":"https://fuldig.hs-fulda.de/viewer/rest/iiif/manifests/PPN439972744/canvas/11","resource":{"@id":"https://fuldig.hs-fulda.de/viewer/rest/image/PPN439972744/00000011.tif/full/!200,220/0/default.jpg","@type":"dcTypes:Image","width":3991,"height":5899,"format":"image/jpeg","service":{"@context":"http://iiif.io/api/image/2/context.json","@id":"https://fuldig.hs-fulda.de/viewer/rest/image/PPN439972744/00000011.tif","profile":"http://iiif.io/api/image/2/level2.json"}}}],"otherContent":[{"@id":"https://fuldig.hs-fulda.de/viewer/rest/iiif/manifests/PPN439972744/list/11/PDF","@type":"sc:AnnotationList","label":"PDF"}]},{"@id":"https://fuldig.hs-fulda.de/viewer/rest/iiif/manifests/PPN439972744/canvas/12","@type":"sc:Canvas","label":" - ","thumbnail":{"@id":"https://fuldig.hs-fulda.de/viewer/rest/image/PPN439972744/00000012.tif/full/!200,220/0/default.jpg","@type":"dcTypes:Image"},"rendering":{"@id":"https://fuldig.hs-fulda.de/viewer/image/PPN439972744/12/","label":"goobi viewer","format":"text/html"},"within":"https://fuldig.hs-fulda.de/viewer/rest/iiif/manifests/PPN439972744/sequence/basic","width":4185,"height":5899,"images":[{"@id":"https://fuldig.hs-fulda.de/viewer/rest/iiif/manifests/PPN439972744/canvas/12/image/1","@type":"oa:Annotation","motivation":"sc:painting","on":"https://fuldig.hs-fulda.de/viewer/rest/iiif/manifests/PPN439972744/canvas/12","resource":{"@id":"https://fuldig.hs-fulda.de/viewer/rest/image/PPN439972744/00000012.tif/full/!200,220/0/default.jpg","@type":"dcTypes:Image","width":4185,"height":5899,"format":"image/jpeg","service":{"@context":"http://iiif.io/api/image/2/context.json","@id":"https://fuldig.hs-fulda.de/viewer/rest/image/PPN439972744/00000012.tif","profile":"http://iiif.io/api/image/2/level2.json"}}}],"otherContent":[{"@id":"https://fuldig.hs-fulda.de/viewer/rest/iiif/manifests/PPN439972744/list/12/PDF","@type":"sc:AnnotationList","label":"PDF"}]},{"@id":"https://fuldig.hs-fulda.de/viewer/rest/iiif/manifests/PPN439972744/canvas/13","@type":"sc:Canvas","label":" - ","thumbnail":{"@id":"https://fuldig.hs-fulda.de/viewer/rest/image/PPN439972744/00000013.tif/full/!200,220/0/default.jpg","@type":"dcTypes:Image"},"rendering":{"@id":"https://fuldig.hs-fulda.de/viewer/image/PPN439972744/13/","label":"goobi viewer","format":"text/html"},"within":"https://fuldig.hs-fulda.de/viewer/rest/iiif/manifests/PPN439972744/sequence/basic","width":3539,"height":2486,"images":[{"@id":"https://fuldig.hs-fulda.de/viewer/rest/iiif/manifests/PPN439972744/canvas/13/image/1","@type":"oa:Annotation","motivation":"sc:painting","on":"https://fuldig.hs-fulda.de/viewer/rest/iiif/manifests/PPN439972744/canvas/13","resource":{"@id":"https://fuldig.hs-fulda.de/viewer/rest/image/PPN439972744/00000013.tif/full/!200,220/0/default.jpg","@type":"dcTypes:Image","width":3539,"height":2486,"format":"image/jpeg","service":{"@context":"http://iiif.io/api/image/2/context.json","@id":"https://fuldig.hs-fulda.de/viewer/rest/image/PPN439972744/00000013.tif","profile":"http://iiif.io/api/image/2/level2.json"}}}],"otherContent":[{"@id":"https://fuldig.hs-fulda.de/viewer/rest/iiif/manifests/PPN439972744/list/13/PDF","@type":"sc:AnnotationList","label":"PDF"}]}],"viewingDirection":"left-to-right"}],"structures":[{"@id":"https://fuldig.hs-fulda.de/viewer/rest/iiif/manifests/PPN439972744/range/LOG_0000","@type":"sc:Range","label":"CONTENT","viewingHint":"top"}]}